JakeSilbersteinMachineLearning/__init__.py
JakeSilbersteinMachineLearning/basic/__init__.py
JakeSilbersteinMachineLearning/basic/layers.py
JakeSilbersteinMachineLearning/basic/model.py
JakeSilbersteinMachineLearning/basic/optimizers.py
JakeSilbersteinMachineLearning/beyop/__init__.py
JakeSilbersteinMachineLearning/beyop/beyop.py
JakeSilbersteinMachineLearning/cnn/__init__.py
JakeSilbersteinMachineLearning/cnn/layers.py
JakeSilbersteinMachineLearning/rl/__init__.py
JakeSilbersteinMachineLearning/rnn/__init__.py
JakeSilbersteinMachineLearning/transformer/__init__.py
JakeSilbersteinMachineLearning/utils/__init__.py
JakeSilbersteinMachineLearning/utils/utils.py
JakeSilbersteinMachineLearning-0.2.14.dist-info/METADATA
JakeSilbersteinMachineLearning-0.2.14.dist-info/WHEEL
JakeSilbersteinMachineLearning-0.2.14.dist-info/top_level.txt
JakeSilbersteinMachineLearning-0.2.14.dist-info/RECORD
