Metadata-Version: 2.1
Name: JakeSilbersteinMachineLearning
Version: 0.2.14
Summary: Non-Functional Machine Learning Library
Author: Jake Silberstein
Author-email: jake.silberstein8@gmail.com
Keywords: python,Neural Networks,AI,CNN,RNN,DQN,LSTM,GRU,Transformers,Beyesian Optimization
Classifier: Development Status :: 1 - Planning
Classifier: Intended Audience :: Developers
Classifier: Programming Language :: Python :: 3
Classifier: Operating System :: Unix
Classifier: Operating System :: MacOS :: MacOS X
Classifier: Operating System :: Microsoft :: Windows
Requires-Dist: numpy
Requires-Dist: scipy
Requires-Dist: scikit-learn
Requires-Dist: matplotlib
Requires-Dist: joblib
Requires-Dist: opencv-python
Requires-Dist: gym
Requires-Dist: python-abc
Requires-Dist: scikit-optimize
